Metadata-Version: 2.1
Name: django-admin-model-list-order
Version: 0.0.4
Summary: Custom ordering for models in the admin app.
Home-page: https://github.com/Vikrant-Arya/django-admin-model-list-order
Author: Vikrant Arya
Author-email: vikrantarya21@gmail.com
License: BSD
Keywords: django-admin-model-list-order
Platform: UNKNOWN
Classifier: Framework :: Django
Classifier: Intended Audience :: Developers
Classifier: License :: OSI Approved :: BSD License
Classifier: Natural Language :: English
Classifier: Programming Language :: Python :: 2.7
Classifier: Programming Language :: Python :: 3.4
Classifier: Programming Language :: Python :: 3.5
Classifier: Programming Language :: Python :: 3.6
Classifier: Programming Language :: Python :: 3.7
